lackey/__init__.py
lackey/access_control.py
lackey/advanced_search.py
lackey/auth.py
lackey/cli.py
lackey/core.py
lackey/dag_analyzer.py
lackey/dependencies.py
lackey/dependency_analysis.py
lackey/file_ops.py
lackey/indexing.py
lackey/models.py
lackey/monitoring.py
lackey/notes.py
lackey/notifications.py
lackey/path_security.py
lackey/py.typed
lackey/rate_limiting.py
lackey/schema_validation.py
lackey/secure_config.py
lackey/security.py
lackey/security_audit.py
lackey/security_monitoring.py
lackey/storage.py
lackey/template_generator.py
lackey/template_registry.py
lackey/template_validation.py
lackey/template_versioning.py
lackey/templates.py
lackey/validation.py
lackey/workflow.py
lackey/builtin_templates/architect.yaml
lackey/builtin_templates/basic-project.yaml
lackey/builtin_templates/developer.yaml
lackey/builtin_templates/manager.yaml
lackey/builtin_templates/software-workflow.yaml
lackey/builtin_templates/sysadmin.yaml
lackey/builtin_templates/writer.yaml
lackey/builtin_templates/rules/architect-rules.md
lackey/builtin_templates/rules/developer-rules.md
lackey/builtin_templates/rules/general-rules.md
lackey/builtin_templates/rules/manager-rules.md
lackey/builtin_templates/rules/sysadmin-rules.md
lackey/builtin_templates/rules/writer-rules.md
lackey/config/config_manager.py
lackey/mcp/__init__.py
lackey/mcp/cli.py
lackey/mcp/context_manager.py
lackey/mcp/enhanced_gateway_router.py
lackey/mcp/error_handling.py
lackey/mcp/gateway_router.py
lackey/mcp/gateway_schema_definitions.py
lackey/mcp/gateway_schemas.py
lackey/mcp/intent_classifier.py
lackey/mcp/lackey_suggest.py
lackey/mcp/lackey_validate.py
lackey/mcp/parameter_mapper.py
lackey/mcp/routing_monitor.py
lackey/mcp/routing_tables.py
lackey/mcp/schema_context_intelligence.py
lackey/mcp/server.py
lackey/mcp/tier1_errors.py
lackey/mcp/tier2_errors.py
lackey/mcp/tier3_errors.py
lackey/mcp/tool_analytics.py
lackey/mcp/tool_recognition_test.py
lackey/mcp/tool_selection_benchmark.py
lackey/mcp/gateways/__init__.py
lackey_mcp-5.0.1.dist-info/licenses/LICENSE
lackey_mcp-5.0.1.dist-info/METADATA
lackey_mcp-5.0.1.dist-info/WHEEL
lackey_mcp-5.0.1.dist-info/entry_points.txt
lackey_mcp-5.0.1.dist-info/top_level.txt
lackey_mcp-5.0.1.dist-info/RECORD
